pretenders/__init__.py
pretenders/client/__init__.py
pretenders/client/http.py
pretenders/client/smtp.py
pretenders/common/__init__.py
pretenders/common/constants.py
pretenders/common/exceptions.py
pretenders/common/http.py
pretenders/common/pretender.py
pretenders/common/smtp.py
pretenders/common/compat/__init__.py
pretenders/common/compat/dictconfig.py
pretenders/common/compat/ordered_dict.py
pretenders/common/tests/__init__.py
pretenders/common/tests/test_match_rule.py
pretenders/server/__init__.py
pretenders/server/base.py
pretenders/server/data.py
pretenders/server/log.py
pretenders/server/maintain.py
pretenders/server/middleware.py
pretenders/server/pretender.py
pretenders/server/server.py
pretenders/server/settings.py
pretenders/server/utils.py
pretenders/server/views.py
pretenders/server/apps/__init__.py
pretenders/server/apps/history.py
pretenders/server/apps/preset.py
pretenders/server/apps/pretender.py
pretenders/server/apps/replay.py
pretenders/server/mock_servers/__init__.py
pretenders/server/mock_servers/http/__init__.py
pretenders/server/mock_servers/http/handler.py
pretenders/server/mock_servers/smtp/__init__.py
pretenders/server/mock_servers/smtp/handler.py
pretenders/server/mock_servers/smtp/server.py
pretenders/server/mock_servers/ssh/__init__.py
pretenders/server/mock_servers/ssh/server.py
pretenders/server/static/favicon.ico
pretenders/server/static/bootstrap/css/bootstrap-responsive.min.css
pretenders/server/static/bootstrap/css/bootstrap.min.css
pretenders/server/static/bootstrap/img/glyphicons-halflings-white.png
pretenders/server/static/bootstrap/img/glyphicons-halflings.png
pretenders/server/static/bootstrap/js/bootstrap.min.js
pretenders/server/static/css/app.css
pretenders/server/static/font-awesome/css/font-awesome.min.css
pretenders/server/static/font-awesome/font/FontAwesome.otf
pretenders/server/static/font-awesome/font/fontawesome-webfont.eot
pretenders/server/static/font-awesome/font/fontawesome-webfont.svg
pretenders-1.4.5.dist-info/AUTHORS
pretenders-1.4.5.dist-info/METADATA
pretenders-1.4.5.dist-info/WHEEL
pretenders-1.4.5.dist-info/top_level.txt
pretenders-1.4.5.dist-info/RECORD
