Metadata-Version: 2.1
Name: pretenders
Version: 1.4.5
Summary: Fake servers for testing
Home-page: https://github.com/pretenders/pretenders
Author: Carles Barrobés, Alex Couper
Author-email: carles@barrobes.com, amcouper@gmail.com
License: UNKNOWN
Platform: UNKNOWN
Classifier: Development Status :: 4 - Beta
Classifier: Environment :: Console
Classifier: Intended Audience :: Developers
Classifier: License :: OSI Approved :: GNU Library or Lesser General Public License (LGPL)
Classifier: Operating System :: OS Independent
Classifier: Programming Language :: Python :: 3
Classifier: Topic :: Software Development :: Testing
License-File: AUTHORS
Requires-Dist: bottle
Requires-Dist: argparse
Provides-Extra: ui
Requires-Dist: jinja2 ; extra == 'ui'
